pycount_a5/__init__.py
pycount_a5/plotting.py
pycount_a5/pycount_a5.py
pycount_a5-0.1.0.dist-info/LICENSE
pycount_a5-0.1.0.dist-info/METADATA
pycount_a5-0.1.0.dist-info/WHEEL
pycount_a5-0.1.0.dist-info/RECORD
