Metadata-Version: 2.1
Name: pycount_a5
Version: 0.1.0
Summary: Assignment 5 for UBC's DSCI310 course. Creating a toy python package.
License: MIT
Author: Jade Bouchard
Requires-Python: >=3.9
Classifier: License :: OSI Approved :: MIT License
Classifier: Programming Language :: Python :: 3
Classifier: Programming Language :: Python :: 3.9
Classifier: Programming Language :: Python :: 3.10
Classifier: Programming Language :: Python :: 3.11
Classifier: Programming Language :: Python :: 3.12
Requires-Dist: docutils (>=0.20.1,<0.21.0)
Requires-Dist: matplotlib (>=3.8.3)
Requires-Dist: myst-nb (>=1.0.0,<2.0.0)
